configobj/__init__.py
configobj/_version.py
configobj/validate.py
configobj-5.0.7.dist-info/LICENSE
configobj-5.0.7.dist-info/METADATA
configobj-5.0.7.dist-info/WHEEL
configobj-5.0.7.dist-info/top_level.txt
configobj-5.0.7.dist-info/RECORD
